{
  "campos_basicos": [
    {
      "campo": "PROTOCOLO",
      "tipo": "texto",
      "descricao": "Número do protocolo ou FAR",
      "obrigatorio": true
    },
    {
      "campo": "DATA_VISTORIA",
      "tipo": "data",
      "descricao": "Data da realização da vistoria",
      "formato": "DD/MM/AAAA",
      "obrigatorio": true
    },
    {
      "campo": "NOME_CLIENTE",
      "tipo": "texto",
      "descricao": "Nome completo do cliente",
      "obrigatorio": true
    },
    {
      "campo": "TIPO_EMPREENDIMENTO",
      "tipo": "texto",
      "descricao": "Tipo do empreendimento (Residencial, Comercial, etc.)",
      "obrigatorio": true
    },
    {
      "campo": "ENDERECO",
      "tipo": "texto",
      "descricao": "Endereço completo da edificação",
      "obrigatorio": true
    },
    {
      "campo": "CIDADE",
      "tipo": "texto",
      "descricao": "Nome da cidade",
      "obrigatorio": true
    },
    {
      "campo": "UF",
      "tipo": "texto",
      "descricao": "Sigla do estado",
      "tamanho_maximo": 2,
      "obrigatorio": true
    },
    {
      "campo": "ASSUNTO",
      "tipo": "texto",
      "descricao": "Assunto da vistoria",
      "valor_padrao": "AT - BRA - PERMEABILIDADE - Telhado com vazamento Geral",
      "obrigatorio": true
    },
    {
      "campo": "NOME_TECNICO",
      "tipo": "texto",
      "descricao": "Nome do técnico responsável pela vistoria",
      "obrigatorio": true
    },
    {
      "campo": "DEPARTAMENTO",
      "tipo": "texto",
      "descricao": "Departamento do técnico",
      "valor_padrao": "Assistência Técnica",
      "obrigatorio": true
    },
    {
      "campo": "UNIDADE",
      "tipo": "texto",
      "descricao": "Unidade regional",
      "obrigatorio": true
    },
    {
      "campo": "NOME_COORDENADOR",
      "tipo": "texto",
      "descricao": "Nome do coordenador responsável",
      "obrigatorio": true
    },
    {
      "campo": "NOME_GERENTE",
      "tipo": "texto",
      "descricao": "Nome do gerente responsável",
      "obrigatorio": true
    },
    {
      "campo": "REGIONAL",
      "tipo": "texto",
      "descricao": "Nome da regional",
      "obrigatorio": true
    },
    {
      "campo": "ESPESSURA",
      "tipo": "numero",
      "descricao": "Espessura da telha em mm",
      "valores_possiveis": [5, 6, 8],
      "valor_padrao": 6,
      "obrigatorio": true
    },
    {
      "campo": "MODELO_TELHA",
      "tipo": "texto",
      "descricao": "Modelo específico da telha",
      "valor_padrao": "Ondulada",
      "obrigatorio": true
    },
    {
      "campo": "ANOS_GARANTIA",
      "tipo": "numero",
      "descricao": "Anos de garantia padrão",
      "valor_padrao": 5,
      "obrigatorio": true
    },
    {
      "campo": "ANOS_GARANTIA_SISTEMA_COMPLETO",
      "tipo": "numero",
      "descricao": "Anos de garantia para sistema completo",
      "valor_padrao": 10,
      "obrigatorio": true
    },
    {
      "campo": "QUANTIDADE",
      "tipo": "numero",
      "descricao": "Quantidade de telhas",
      "obrigatorio": true
    },
    {
      "campo": "AREA",
      "tipo": "numero",
      "descricao": "Área coberta aproximada em m²",
      "obrigatorio": true
    },
    {
      "campo": "ANOS_GARANTIA_TOTAL",
      "tipo": "numero",
      "descricao": "Anos totais de garantia do produto",
      "valor_padrao": 10,
      "obrigatorio": true
    },
    {
      "campo": "RESULTADO_RECLAMACAO",
      "tipo": "selecao",
      "descricao": "Resultado final da análise",
      "valores_possiveis": ["PROCEDENTE", "IMPROCEDENTE"],
      "valor_padrao": "IMPROCEDENTE",
      "obrigatorio": true
    },
    {
      "campo": "NUMERO_REGISTRO",
      "tipo": "texto",
      "descricao": "Número de registro CREA/CAU do técnico",
      "obrigatorio": true
    }
  ],
  "nao_conformidades": [
    {
      "id": 1,
      "titulo": "Armazenagem Incorreta",
      "campo": "NAO_CONFORMIDADE_1",
      "campo_lista": "Armazenagem Incorreta"
    },
    {
      "id": 2,
      "titulo": "Carga Permanente sobre as Telhas",
      "campo": "NAO_CONFORMIDADE_2",
      "campo_lista": "Carga Permanente sobre as Telhas"
    },
    {
      "id": 3,
      "titulo": "Corte de Canto Incorreto ou Ausente",
      "campo": "NAO_CONFORMIDADE_3",
      "campo_lista": "Corte de Canto Incorreto ou Ausente"
    },
    {
      "id": 4,
      "titulo": "Estrutura Desalinhada",
      "campo": "NAO_CONFORMIDADE_4",
      "campo_lista": "Estrutura Desalinhada"
    },
    {
      "id": 5,
      "titulo": "Fixação Irregular das Telhas",
      "campo": "NAO_CONFORMIDADE_5",
      "campo_lista": "Fixação Irregular das Telhas"
    },
    {
      "id": 6,
      "titulo": "Inclinação da Telha Inferior ao Recomendado",
      "campo": "NAO_CONFORMIDADE_6",
      "campo_lista": "Inclinação da Telha Inferior ao Recomendado"
    },
    {
      "id": 7,
      "titulo": "Marcas de Caminhamento sobre o Telhado",
      "campo": "NAO_CONFORMIDADE_7",
      "campo_lista": "Marcas de Caminhamento sobre o Telhado"
    },
    {
      "id": 8,
      "titulo": "Balanço Livre do Beiral Incorreto",
      "campo": "NAO_CONFORMIDADE_8",
      "campo_lista": "Balanço Livre do Beiral Incorreto"
    },
    {
      "id": 9,
      "titulo": "Número de Apoios e Vão Livre Inadequados",
      "campo": "NAO_CONFORMIDADE_9",
      "campo_lista": "Número de Apoios e Vão Livre Inadequados"
    },
    {
      "id": 10,
      "titulo": "Recobrimento Incorreto",
      "campo": "NAO_CONFORMIDADE_10",
      "campo_lista": "Recobrimento Incorreto"
    },
    {
      "id": 11,
      "titulo": "Sentido de Montagem Incorreto",
      "campo": "NAO_CONFORMIDADE_11",
      "campo_lista": "Sentido de Montagem Incorreto"
    },
    {
      "id": 12,
      "titulo": "Uso de Cumeeira Cerâmica",
      "campo": "NAO_CONFORMIDADE_12",
      "campo_lista": "Uso de Cumeeira Cerâmica"
    },
    {
      "id": 13,
      "titulo": "Uso de Argamassa em Substituição a Peças Complementares",
      "campo": "NAO_CONFORMIDADE_13",
      "campo_lista": "Uso de Argamassa em Substituição a Peças Complementares"
    },
    {
      "id": 14,
      "titulo": "Fixação de Acessórios Complementares Realizada de Forma Inadequada",
      "campo": "NAO_CONFORMIDADE_14",
      "campo_lista": "Fixação de Acessórios Complementares Realizada de Forma Inadequada"
    }
  ]
}
